tf_spectral/__init__.py
tf_spectral/spectral.py
tf_spectral-0.1.dist-info/DESCRIPTION.rst
tf_spectral-0.1.dist-info/METADATA
tf_spectral-0.1.dist-info/RECORD
tf_spectral-0.1.dist-info/WHEEL
tf_spectral-0.1.dist-info/metadata.json
tf_spectral-0.1.dist-info/top_level.txt
