Metadata-Version: 2.0
Name: tf-spectral
Version: 0.1
Summary: Spectrogram tools using tensorflow
Home-page: http://github.com/zekearneodo/tf_spectral
Author: Zeke Arneodo
Author-email: earneodo@ucsd.edu
License: GNU3
Platform: UNKNOWN
Requires-Dist: numpy
Requires-Dist: semver
Requires-Dist: tensorflow
